[
  { "name": "Café Mogador", "url": "https://maps.google.com/?q=Cafe+Mogador+NYC" },
  { "name": "Caravan of Dreams", "url": "https://maps.google.com/?q=Caravan+of+Dreams+NYC" },
  { "name": "DntWatchTV", "url": "https://www.google.com/search?q=DntWatchTV+317+album", "expandToLine": true },
  { "name": "Tame Impala", "url": "https://www.google.com/search?q=Tame+Impala+Innerspeaker+album", "expandToLine": true },
  { "name": "Jay-Z", "url": "https://www.google.com/search?q=Jay-Z+The+Blueprint+album", "expandToLine": true },
  { "name": "Nas", "url": "https://www.google.com/search?q=Nas+Illmatic+album", "expandToLine": true },
  { "name": "50 Cent", "url": "https://www.google.com/search?q=50+Cent+The+Massacre+album", "expandToLine": true },
  { "name": "Westside Gunn", "url": "https://www.google.com/search?q=Westside+Gunn+rapper", "expandToLine": true },
  { "name": "Gathers", "url": "https://maps.google.com/?q=Gathers+NYC" },
  { "name": "Cipriani Downtown", "url": "https://maps.google.com/?q=Cipriani+Downtown+NYC" },
  { "name": "Sweet Chick", "url": "https://maps.google.com/?q=Sweet+Chick+NYC" },
  { "name": "Las' Lap", "url": "https://maps.google.com/?q=Las+Lap+NYC" },
  { "name": "Margaritaville", "url": "https://maps.google.com/?q=Margaritaville+NYC" },
  { "name": "Clockwork Bar", "url": "https://maps.google.com/?q=Clockwork+Bar+NYC" },
  { "name": "Scarr's Pizza", "url": "https://maps.google.com/?q=Scarrs+Pizza+NYC" },
  { "name": "Black Music", "url": "https://www.google.com/search?q=Black+Music+LeRoi+Jones+book", "expandToLine": true },
  { "name": "Assata: An Autobiography", "url": "https://www.google.com/search?q=Assata+An+Autobiography+book", "expandToLine": true },
  { "name": "The Alchemist", "url": "https://www.google.com/search?q=The+Alchemist+Paulo+Coelho+book", "expandToLine": true },

  { "name": "Quarters", "url": "https://www.google.com/search?q=Quarters+band+NYC", "expandToLine": true },
  { "name": "Simon & Garfunkel", "url": "https://www.google.com/search?q=Simon+%26+Garfunkel+Bookends+album", "expandToLine": true },
  { "name": "Aoris", "url": "https://www.google.com/search?q=Aoris+Greece+In+Existence+album", "expandToLine": true },
  { "name": "Carlita", "url": "https://www.google.com/search?q=Carlita+Sentimental+album", "expandToLine": true },
  { "name": "Justin Beiber", "url": "https://www.google.com/search?q=Justin+Bieber+My+World+EP", "expandToLine": true },

  { "name": "Forgtmenot", "url": "https://maps.google.com/?q=Forgtmenot+138+Division+St+New+York+NY" },
  { "name": "Santo Tacos", "url": "https://www.eatsantotaco.com/" },
  { "name": "Felix", "url": "https://www.felixnyc.com/" },

  { "name": "Baker Falls", "url": "https://bakerfalls.com/" },
  { "name": "Kettle of Fish", "url": "https://www.kettleoffishnyc.com/" },
  { "name": "The Library", "url": "https://maps.google.com/?q=The+Library+7+Ave+A+New+York+NY" },
  { "name": "Milano's", "url": "https://milanosbar.com/" },

  { "name": "Abundance", "url": "https://www.google.com/search?q=Abundance+Ezra+Klein+2025+book", "expandToLine": true },
  { "name": "Emerald Cities", "url": "https://www.google.com/search?q=Emerald+Cities+Joan+Fitzgerald+2010+book", "expandToLine": true },
  { "name": "The Artists Way", "url": "https://www.google.com/search?q=The+Artists+Way+Julia+Cameron+book", "expandToLine": true },
  { "name": "Ezra Klein", "url": "https://www.google.com/search?q=Ezra+Klein+author", "expandToLine": true },
  { "name": "Joan Fitzgerald", "url": "https://www.google.com/search?q=Joan+Fitzgerald+Emerald+Cities+author", "expandToLine": true },
  { "name": "Julia Cameron", "url": "https://www.google.com/search?q=Julia+Cameron+The+Artists+Way+author", "expandToLine": true },

  { "name": "Dave Matthews Band", "url": "https://www.google.com/search?q=Dave+Matthews+Band", "expandToLine": true },
  { "name": "The Central Park Concert", "url": "https://www.google.com/search?q=Dave+Matthews+Band+The+Central+Park+Concert+2003", "expandToLine": true },
  { "name": "John Mayer", "url": "https://www.google.com/search?q=John+Mayer+musician", "expandToLine": true },
  { "name": "Where the Light is", "url": "https://www.google.com/search?q=John+Mayer+Where+the+Light+is+2008+album", "expandToLine": true },
  { "name": "Alice Phoebe Lou", "url": "https://www.google.com/search?q=Alice+Phoebe+Lou+musician", "expandToLine": true },
  { "name": "Child's Play", "url": "https://www.google.com/search?q=Alice+Phoebe+Lou+Child%27s+Play+2021+album", "expandToLine": true },
  { "name": "Beck", "url": "https://www.google.com/search?q=Beck+musician+Guero", "expandToLine": true },
  { "name": "Guero", "url": "https://www.google.com/search?q=Beck+Guero+2005+album", "expandToLine": true },
  { "name": "Horse Vision", "url": "https://www.google.com/search?q=Horse+Vision+band+NYC", "expandToLine": true },
  { "name": "No Signal", "url": "https://www.google.com/search?q=No+Signal+Light+Sound+Design+NYC", "expandToLine": true },
  { "name": "Jacob Collier", "url": "https://www.google.com/search?q=Jacob+Collier+musician", "expandToLine": true },

  { "name": "Nightclub 101", "url": "https://maps.google.com/?q=Nightclub+101+NYC" },
  { "name": "Night Club 101", "url": "https://maps.google.com/?q=Nightclub+101+NYC" },
  { "name": "Blue Note Jazz Club", "url": "https://maps.google.com/?q=Blue+Note+Jazz+Club+New+York+NY" },
  { "name": "Fanelli Cafe", "url": "https://maps.google.com/?q=Fanelli+Cafe+New+York+NY" },
  { "name": "The Met Cloisters", "url": "https://maps.google.com/?q=The+Met+Cloisters+New+York+NY" },
  { "name": "KGB", "url": "https://maps.google.com/?q=KGB+Bar+New+York+NY" },
  { "name": "Under St. Marks", "url": "https://maps.google.com/?q=Under+St+Marks+New+York+NY" },
  { "name": "Soho Playhouse", "url": "https://maps.google.com/?q=Soho+Playhouse+New+York+NY" },
  { "name": "Rivington", "url": "https://maps.google.com/?q=Rivington+Music+New+York+NY" },
  { "name": "6/8 Studios", "url": "https://maps.google.com/?q=6%2F8+Studios+New+York+NY" },
  { "name": "Pirate", "url": "https://maps.google.com/?q=Pirate+Studios+New+York+NY" },
  { "name": "Mercy Sound", "url": "https://maps.google.com/?q=Mercy+Sound+New+York+NY" },
  { "name": "Melophobe", "url": "https://maps.google.com/?q=Melophobe+New+York+NY" },

  { "name": "Louise Yeung", "url": "https://www.google.com/search?q=Louise+Yeung+NYC+Chief+Climate+Officer", "expandToLine": true },
  { "name": "Rawa Duwaji", "url": "https://www.google.com/search?q=Rawa+Duwaji+NYC+First+Lady", "expandToLine": true },
  { "name": "Liam Mckeon", "url": "https://www.google.com/search?q=Liam+Mckeon+artist+photographer", "expandToLine": true },
  { "name": "Jordin De La Rosa", "url": "https://www.google.com/search?q=Jordin+De+La+Rosa+photographer", "expandToLine": true },
  { "name": "Bones Gilmore", "url": "https://www.google.com/search?q=Bones+Gilmore+artist", "expandToLine": true },

  { "name": "Crowdrise", "url": "https://www.google.com/search?q=Crowdrise+NYC+green", "expandToLine": true },
  { "name": "StreetEasy", "url": "https://www.google.com/search?q=StreetEasy+NYC+app", "expandToLine": true },
  { "name": "NYC Tree Map", "url": "https://www.google.com/search?q=NYC+Tree+Map+urban+forest", "expandToLine": true }
]
